scripts/__init__.py
scripts/analysis_formatter.py
scripts/analysis_log_writer.py
scripts/analysis_validator.py
scripts/db.py
scripts/embed.py
scripts/export.py
scripts/html_extract.py
scripts/migrate.py
scripts/resolve-project.sh
scripts/update-readme-stats.sh
scripts/usage_capture.py
scripts/validate.py
scripts/hooks/strip-coauthors.sh
realitycheck-0.3.0.dist-info/METADATA
realitycheck-0.3.0.dist-info/WHEEL
realitycheck-0.3.0.dist-info/entry_points.txt
realitycheck-0.3.0.dist-info/licenses/LICENSE
realitycheck-0.3.0.dist-info/RECORD
