Metadata-Version: 2.4
Name: realitycheck
Version: 0.3.0
Summary: Framework for rigorous, systematic analysis of claims, sources, predictions, and argument chains
Project-URL: Homepage, https://github.com/lhl/realitycheck
Project-URL: Repository, https://github.com/lhl/realitycheck
Project-URL: Documentation, https://github.com/lhl/realitycheck/blob/main/README.md
Author-email: Leonard Lin <lhl@lhl.org>
License: Apache-2.0
License-File: LICENSE
Keywords: analysis,claims,epistemics,lancedb,predictions,sources
Classifier: Development Status :: 3 - Alpha
Classifier: Intended Audience :: Developers
Classifier: Intended Audience :: Science/Research
Classifier: License :: OSI Approved :: Apache Software License
Classifier: Programming Language :: Python :: 3
Classifier: Programming Language :: Python :: 3.11
Classifier: Programming Language :: Python :: 3.12
Classifier: Topic :: Scientific/Engineering
Requires-Python: >=3.11
Requires-Dist: beautifulsoup4>=4.12.0
Requires-Dist: lancedb>=0.18.0
Requires-Dist: pyarrow>=18.0.0
Requires-Dist: pyyaml>=6.0
Requires-Dist: sentence-transformers>=3.0.0
Requires-Dist: tabulate>=0.9.0
Provides-Extra: dev
Requires-Dist: jinja2>=3.1.0; extra == 'dev'
Requires-Dist: pytest-cov>=4.0.0; extra == 'dev'
Requires-Dist: pytest>=8.0.0; extra == 'dev'
